eqsolver/ISLM.py
eqsolver/__init__.py
eqsolver/gasConsts.py
eqsolver/gasEquations.py
eqsolver/solver.py
eqsolver-0.2.4.dist-info/METADATA
eqsolver-0.2.4.dist-info/WHEEL
eqsolver-0.2.4.dist-info/top_level.txt
eqsolver-0.2.4.dist-info/RECORD
